<?xml version="1.0" encoding="UTF-8"?>
<Tokens version="1.0">
	<File path="Classes/NSKitInternetDoctor.html">
		
		<Token>
			<TokenIdentifier>//apple_ref/occ/cl/NSKitInternetDoctor</TokenIdentifier>
			<Abstract type="html">Holds a reference to the default URL to ping.</Abstract>
			<DeclaredIn>NSKitInternetDoctor.h</DeclaredIn>
			
			<NodeRef refid="2"/>
		</Token>
		
		
		<Token>
			<TokenIdentifier>//apple_ref/occ/instm/NSKitInternetDoctor/setConnected:</TokenIdentifier>
			<Abstract type="html"></Abstract>
			<DeclaredIn>NSKitInternetDoctor.h</DeclaredIn>			
			
			<Declaration>@property (nonatomic, assign) BOOL connected</Declaration>
			
			
			<Anchor>//api/name/connected</Anchor>
            <NodeRef refid="2"/>
		</Token>
		
		<Token>
			<TokenIdentifier>//apple_ref/occ/instm/NSKitInternetDoctor/connected</TokenIdentifier>
			<Abstract type="html"></Abstract>
			<DeclaredIn>NSKitInternetDoctor.h</DeclaredIn>			
			
			<Declaration>@property (nonatomic, assign) BOOL connected</Declaration>
			
			
			<Anchor>//api/name/connected</Anchor>
            <NodeRef refid="2"/>
		</Token>
		
		<Token>
			<TokenIdentifier>//apple_ref/occ/instp/NSKitInternetDoctor/connected</TokenIdentifier>
			<Abstract type="html"></Abstract>
			<DeclaredIn>NSKitInternetDoctor.h</DeclaredIn>			
			
			<Declaration>@property (nonatomic, assign) BOOL connected</Declaration>
			
			
			<Anchor>//api/name/connected</Anchor>
            <NodeRef refid="2"/>
		</Token>
		
		<Token>
			<TokenIdentifier>//apple_ref/occ/clm/NSKitInternetDoctor/shared</TokenIdentifier>
			<Abstract type="html"></Abstract>
			<DeclaredIn>NSKitInternetDoctor.h</DeclaredIn>			
			
			<Declaration>+ (NSKitInternetDoctor *)shared</Declaration>
			
			
			<Anchor>//api/name/shared</Anchor>
            <NodeRef refid="2"/>
		</Token>
		
		<Token>
			<TokenIdentifier>//apple_ref/occ/instm/NSKitInternetDoctor/pingServer</TokenIdentifier>
			<Abstract type="html"></Abstract>
			<DeclaredIn>NSKitInternetDoctor.h</DeclaredIn>			
			
			<Declaration>- (void)pingServer</Declaration>
			
			
			<Anchor>//api/name/pingServer</Anchor>
            <NodeRef refid="2"/>
		</Token>
		
		<Token>
			<TokenIdentifier>//apple_ref/occ/instm/NSKitInternetDoctor/retry</TokenIdentifier>
			<Abstract type="html"></Abstract>
			<DeclaredIn>NSKitInternetDoctor.h</DeclaredIn>			
			
			<Declaration>- (void)retry</Declaration>
			
			
			<Anchor>//api/name/retry</Anchor>
            <NodeRef refid="2"/>
		</Token>
		
	</File>
</Tokens>